MANIFEST.in
setup.cfg
setup.py
d1_ticket_generator/__init__.py
d1_ticket_generator/mn_deployment_template.yaml
d1_ticket_generator/mn_deployment_ticket_generator.py
d1_ticket_generator/redmine_ticket_generator.py
dataone.ticket_generator.egg-info/PKG-INFO
dataone.ticket_generator.egg-info/SOURCES.txt
dataone.ticket_generator.egg-info/dependency_links.txt
dataone.ticket_generator.egg-info/entry_points.txt
dataone.ticket_generator.egg-info/requires.txt
dataone.ticket_generator.egg-info/top_level.txt