Metadata-Version: 1.0
Name: dataone.ticket-generator
Version: 0.3.3
Summary: Generate a set of Redmine tickets based on YAML template and value files
Home-page: http://dataone.org
Author: DataONE Project
Author-email: developers@dataone.org
License: Apache License, Version 2.0
Platform: UNKNOWN
